hello_juanmosh/__init__.py
hello_juanmosh/hello_juanmosh.py
hello_juanmosh-0.0.3.dist-info/METADATA
hello_juanmosh-0.0.3.dist-info/WHEEL
hello_juanmosh-0.0.3.dist-info/top_level.txt
hello_juanmosh-0.0.3.dist-info/RECORD
