Metadata-Version: 2.1
Name: hello-juanmosh
Version: 0.0.3
Summary: Simple Hello World
Home-page: https://github.com/juanapolinario/calc_package.git
Author: juan
Author-email: apolinario.psi@gmail.com
License: UNKNOWN
Platform: UNKNOWN
Requires-Python: >=3.8
